Workbook

Sheet ReadMe
B1: Section | C1: Description
B2: Project Title | C2: Affirm BNPL Financial & Credit Risk Analytics
B3: Company | C3: Affirm Holdings, Inc.
B4: Period Covered | C4: FY2022–FY2024
B5: Main Data Source | C5: Affirm 10-K Annual Reports
B6: Secondary Dataset | C6: BNPL Kaggle transaction dataset
B7: Excel Scope | C7: 3-statement model, DCF, variance analysis, forecast, scenario analysis
B8: Power BI Scope | C8: Executive summary, P&L analysis, credit risk, cohort analysis, benchmark
B9: Important Note | C9: Affirm financials are based on audited filings. BNPL transaction data is synthetic and used only for transaction-level analysis.

Sheet Source_Tracker
B1: Dataset | C1: File Name | D1: Source Type | E1: Purpose | F1: Status
B2: Affirm FY2022 10-K | C2: affirm_2022_10k.pdf | D2: Annual Report / SEC Filing | E2: Historical financial extraction | F2: Downloaded
B3: Affirm FY2023 10-K | C3: affirm_2023_10k.pdf | D3: Annual Report / SEC Filing | E3: Historical financial extraction | F3: Downloaded
B4: Affirm FY2024 10-K | C4: affirm_2024_10k.pdf | D4: Annual Report / SEC Filing | E4: Historical financial extraction | F4: Downloaded
B5: BNPL Transaction Dataset | C5: bnpl_transactions_raw.csv | D5: Kaggle CSV | E5: Transaction-level credit risk and cohort analysis | F5: Downloaded

Sheet Raw_10K_Extract
A1: Statement | B1: Section | C1: Metric | D1: FY2022 | E1: FY2023 | F1: FY2024 | G1: Unit | H1: Source Page | I1: Notes
A2: Operating Metrics | B2: Platform Scale | C2: GMV | D2: 15483.237 | E2: 20200 | F2: 26600 | G2: USD millions | H2: FY2022 p.61 / FY2024 p.66 | I2: Total transaction volume processed on Affirm platform
A3: Operating Metrics | B3: Consumer Base | C3: Active Consumers | D3: 13.98 | E3: 16.469 | F3: 18.713 | G3: millions | H3: FY2022 p.61 / FY2024 p.66 | I3: Consumers with at least one transaction in last 12 months
A4: Operating Metrics | B4: Merchant Base | C4: Active Merchants | D4: 234.847 | E4: 254 | F4: 303 | G4: thousands | H4: FY2022 p.59 / FY2024 p.5 | I4: Active merchants on Affirm platform
A5: Operating Metrics | B5: Consumer Engagement | C5: Transactions per Active Consumer | D5: 3 | E5: 3.9 | F5: 4.9 | G5: x | H5: FY2022 p.61 / FY2024 p.3 | I5: Average transactions per active consumer
A6: Funding Metrics | B6: Capital Efficiency | C6: Equity Capital % of Total Platform Portfolio | D6: 0.03 | E6: 0.05 | F6: 0.05 | G6: % | H6: FY2022 p.60 / FY2024 p.63 | I6: Shows how much equity capital is required to support total platform portfolio
A7: Funding Metrics | B7: Liquidity / Debt Capacity | C7: Funding Debt Borrowing Capacity | D7: 2934.027 | F7: 5640.126 | G7: USD millions | H7: FY2022 p.75 / FY2024 p.72 | I7: Borrowing capacity from funding debt facilities
A8: Funding Metrics | B8: Liquidity / Debt Usage | C8: Funding Debt Principal Outstanding | D8: 683.395 | F8: 1851.699 | G8: USD millions | H8: FY2022 p.75 / FY2024 p.72 | I8: Amount already drawn/used from funding debt facilities
A9: Income Statement | B9: Revenue | C9: Merchant Network Revenue | D9: 458.511 | E9: 507.6 | F9: 674.607 | G9: USD millions | H9: FY2024 p.66 | I9: Revenue from merchant fees charged on GMV processed through Affirm
A10: Income Statement | B10: Revenue | C10: Card Network Revenue | D10: 100.696 | E10: 119.338 | F10: 151.401 | G10: USD millions | H10: FY2024 p.66 | I10: Revenue from virtual card / card network activity
A11: Income Statement | B11: Revenue | C11: Total Network Revenue | D11: 559.207 | E11: 626.938 | F11: 826.008 | G11: USD millions | H11: FY2024 p.66 | I11: Merchant network revenue + card network revenue
A12: Income Statement | B12: Revenue | C12: Interest Income | D12: 527.88 | E12: 685.217 | F12: 1204.355 | G12: USD millions | H12: FY2024 p.66 | I12: Interest earned on loans held or originated through the platform
A13: Income Statement | B13: Revenue | C13: Gain on Sales of Loans | D13: 196.435 | E13: 188.341 | F13: 197.153 | G13: USD millions | H13: FY2024 p.66 | I13: Gain from selling loans to third-party investors
A14: Income Statement | B14: Revenue | C14: Servicing Income | D14: 65.77 | E14: 87.489 | F14: 95.483 | G14: USD millions | H14: FY2024 p.66 | I14: Fees for servicing loan portfolios owned by third parties
A15: Income Statement | B15: Revenue | C15: Revenue | D15: 1349.292 | E15: 1587.985 | F15: 2322.999 | G15: USD millions | H15: FY2024 p.66 | I15: Total revenue, net
A16: Income Statement | B16: Operating Expenses | C16: Loss on Loan Purchase Commitment | D16: 204.081 | E16: 140.265 | F16: 180.395 | G16: USD millions | H16: FY2024 p.66 | I16: Loss from purchasing loans above fair value under bank partner arrangements
A17: Income Statement | B17: Operating Expenses | C17: Provision for Credit Losses | D17: 255.272 | E17: 331.86 | F17: 460.628 | G17: USD millions | H17: FY2024 p.66 | I17: Estimated expected credit losses on loan portfolio
A18: Income Statement | B18: Operating Expenses | C18: Funding Costs | D18: 69.694 | E18: 183.013 | F18: 344.253 | G18: USD millions | H18: FY2024 p.66 | I18: Cost of funding loan originations and financing facilities
A19: Income Statement | B19: Operating Expenses | C19: Processing and Servicing | D19: 157.814 | E19: 257.343 | F19: 343.249 | G19: USD millions | H19: FY2024 p.66 | I19: Costs to process payments, service loans, and support customers
A20: Income Statement | B20: Operating Expenses | C20: Technology and Data Analytics | D20: 418.643 | E20: 615.818 | F20: 501.857 | G20: USD millions | H20: FY2024 p.66 | I20: Engineering, product, data, analytics, and risk-modeling costs
... A57: Cash Flow Statement | B57: Operating Cash Flow | C57: Net Income / Loss | D57: -707.417 | E57: -985.345 | F57: -517.757 | G57: USD millions | H57: FY2024 p.88 / FY2023 p.91 | I57: Starting point of cash flow statement
A58: Cash Flow Statement | B58: Operating Cash Flow | C58: Depreciation and Amortization | D58: 78.142 | E58: 125.476 | F58: 145.898 | G58: USD millions | H58: FY2024 p.88 / FY2023 p.91 | I58: Non-cash expense added back to net loss | S58: s
A59: Cash Flow Statement | B59: Operating Cash Flow | C59: Stock-Based Compensation | D59: 396.162 | E59: 478.998 | F59: 339.572 | G59: USD millions | H59: FY2024 p.88 / FY2023 p.91 | I59: Non-cash employee equity compensation
A60: Cash Flow Statement | B60: Operating Cash Flow | C60: Provision for Credit Losses | D60: 255.272 | E60: 331.86 | F60: 460.628 | G60: USD millions | H60: FY2024 p.88 / FY2023 p.91 | I60: Expected credit losses added back in operating cash flow
A61: Cash Flow Statement | B61: Operating Cash Flow | C61: Net Cash Used in Operating Activities | D61: -276.624 | E61: -392.075 | F61: -356.332 | G61: USD millions | H61: FY2024 p.88 / FY2023 p.91 | I61: Cash used by core operating activities
A62: Cash Flow Statement | B62: Investing Cash Flow | C62: Purchases of Property, Equipment and Software | D62: -136.337 | E62: -225.452 | F62: -263.204 | G62: USD millions | H62: FY2024 p.88 / FY2023 p.91 | I62: Capital expenditures for software, equipment, and property
A63: Cash Flow Statement | B63: Investing Cash Flow | C63: Net Cash Used in Investing Activities | D63: -1684.709 | E63: -1578.102 | F63: -1231.105 | G63: USD millions | H63: FY2024 p.88 / FY2023 p.91 | I63: Cash used in investing activities
A64: Cash Flow Statement | B64: Financing Cash Flow | C64: Net Cash Provided by Financing Activities | D64: 1915.339 | E64: 1829.566 | F64: 1635.636 | G64: USD millions | H64: FY2024 p.88 / FY2023 p.91 | I64: Cash provided by financing activities
A65: Cash Flow Statement | B65: Free Cash Flow | C65: Free Cash Flow | D65: -412.961 | E65: -617.527 | F65: -619.536 | G65: USD millions | H65: Calculated | I65: Operating cash flow minus purchases of property, equipment and software

Sheet Clean_Financials
A1: Metric Category | B1: Metric | C1: FY2022 | D1: FY2023 | E1: FY2024 | F1: Formula / Logic | G1: Insight Use
A2: Scale | B2: GMV | C2: =_xlfn.XLOOKUP($B2,Raw_10K_Extract!$C:$C,Raw_10K_Extract!$D:$D,"") -> 15483.237 | D2: =_xlfn.XLOOKUP($B2,Raw_10K_Extract!$C:$C,Raw_10K_Extract!$E:$E,"") -> 20200 | E2: =_xlfn.XLOOKUP($B2,Raw_10K_Extract!$C:$C,Raw_10K_Extract!$F:$F,"") -> 26600 | F2: Pulled from Raw_10K_Extract: GMV | G2: Platform transaction volume
A3: Scale | B3: Revenue | C3: =_xlfn.XLOOKUP($B3,Raw_10K_Extract!$C:$C,Raw_10K_Extract!$D:$D,"") -> 1349.292 | D3: =_xlfn.XLOOKUP($B3,Raw_10K_Extract!$C:$C,Raw_10K_Extract!$E:$E,"") -> 1587.985 | E3: =_xlfn.XLOOKUP($B3,Raw_10K_Extract!$C:$C,Raw_10K_Extract!$F:$F,"") -> 2322.999 | F3: Pulled from Raw_10K_Extract: Revenue | G3: Company monetization
A4: Profitability | B4: Operating Income / Loss | C4: =_xlfn.XLOOKUP($B4,Raw_10K_Extract!$C:$C,Raw_10K_Extract!$D:$D,"") -> -866.048 | D4: =_xlfn.XLOOKUP($B4,Raw_10K_Extract!$C:$C,Raw_10K_Extract!$E:$E,"") -> -1200.862 | E4: =_xlfn.XLOOKUP($B4,Raw_10K_Extract!$C:$C,Raw_10K_Extract!$F:$F,"") -> -615.847 | F4: Pulled from Raw_10K_Extract: Operating Income / Loss | G4: Core operating profitability
A5: Profitability | B5: Net Income / Loss | C5: =_xlfn.XLOOKUP($B5,Raw_10K_Extract!$C:$C,Raw_10K_Extract!$D:$D,"") -> -707.417 | D5: =_xlfn.XLOOKUP($B5,Raw_10K_Extract!$C:$C,Raw_10K_Extract!$E:$E,"") -> -985.345 | E5: =_xlfn.XLOOKUP($B5,Raw_10K_Extract!$C:$C,Raw_10K_Extract!$F:$F,"") -> -517.757 | F5: Pulled from Raw_10K_Extract: Net Income / Loss | G5: Final profitability
A6: Cash Flow | B6: Free Cash Flow | C6: =_xlfn.XLOOKUP($B6,Raw_10K_Extract!$C:$C,Raw_10K_Extract!$D:$D,"") -> -412.961 | D6: =_xlfn.XLOOKUP($B6,Raw_10K_Extract!$C:$C,Raw_10K_Extract!$E:$E,"") -> -617.527 | E6: =_xlfn.XLOOKUP($B6,Raw_10K_Extract!$C:$C,Raw_10K_Extract!$F:$F,"") -> -619.536 | F6: Pulled from Raw_10K_Extract: Free Cash Flow | G6: Cash generation after capex
A7: Growth | B7: GMV Growth % | C7: =_xlfn.XLOOKUP($B7,Raw_10K_Extract!$C:$C,Raw_10K_Extract!$D:$D,"") | D7: =D2/C2-1 -> 0.30463675 | E7: =E2/D2-1 -> 0.31683168 | F7: FY2023 = FY2023 GMV / FY2022 GMV - 1; FY2024 = FY2024 GMV / FY2023 GMV - 1 | G7: Current year GMV / prior year GMV - 1
A8: Growth | B8: Revenue Growth % | C8: =_xlfn.XLOOKUP($B8,Raw_10K_Extract!$C:$C,Raw_10K_Extract!$D:$D,"") | D8: =D3/C3-1 -> 0.17690241 | E8: =E3/D3-1 -> 0.46285954 | F8: FY2023 = FY2023 Revenue / FY2022 Revenue - 1; FY2024 = FY2024 Revenue / FY2023 Revenue - 1 | G8: Current year revenue / prior year revenue - 1
A9: Efficiency | B9: Take Rate % | C9: =C3/C2 -> 0.087145343 | D9: =D3/D2 -> 0.078613119 | E9: =E3/E2 -> 0.087330789 | F9: Revenue / GMV | G9: Revenue / GMV
A10: Credit Risk | B10: Credit Loss Rate % | C10: =255.272/C2 -> 0.016486992 | D10: =255.272/D2 -> 0.012637228 | E10: =255.272/E2 -> 0.0095966917 | F10: Provision for Credit Losses / GMV | G10: Provision for Credit Losses / GMV
A11: Profitability | B11: Operating Margin % | C11: =C4/C3 -> -0.64185365 | D11: =D4/D3 -> -0.75621747 | E11: =E4/E3 -> -0.26510859 | F11: Operating Income / Loss / Revenue | G11: Operating Income / Revenue
A12: Profitability | B12: Net Margin % | C12: =C5/C3 -> -0.52428755 | D12: =D5/D3 -> -0.62050019 | E12: =E5/E3 -> -0.22288301 | F12: Net Income / Loss / Revenue | G12: Net Income / Revenue
A13: Cash Flow | B13: Free Cash Flow Margin % | C13: =C6/C3 -> -0.30605755 | D13: =D6/D3 -> -0.38887458 | E13: =E6/E3 -> -0.26669663 | F13: Free Cash Flow / Revenue | G13: Free Cash Flow / Revenue
A14: Customer | B14: Active Consumers | C14: =_xlfn.XLOOKUP($B14,Raw_10K_Extract!$C:$C,Raw_10K_Extract!$D:$D,"") -> 13.98 | D14: =_xlfn.XLOOKUP($B14,Raw_10K_Extract!$C:$C,Raw_10K_Extract!$E:$E,"") -> 16.469 | E14: =_xlfn.XLOOKUP($B14,Raw_10K_Extract!$C:$C,Raw_10K_Extract!$F:$F,"") -> 18.713 | F14: Pulled from Raw_10K_Extract: Active Consumers | G14: Active customer base
A15: Customer | B15: Active Consumer Growth % | C15: =_xlfn.XLOOKUP($B15,Raw_10K_Extract!$C:$C,Raw_10K_Extract!$D:$D,"") | D15: =D14/C14-1 -> 0.17804006 | E15: =E14/D14-1 -> 0.136256 | F15: FY2023 = FY2023 Active Consumers / FY2022 Active Consumers - 1; FY2024 = FY2024 Active Consumers / FY2023 Active Consumers - 1 | G15: Current year active consumers / prior year active consumers - 1
A16: Customer | B16: Transactions per Active Consumer | C16: =_xlfn.XLOOKUP($B16,Raw_10K_Extract!$C:$C,Raw_10K_Extract!$D:$D,"") -> 3 | D16: =_xlfn.XLOOKUP($B16,Raw_10K_Extract!$C:$C,Raw_10K_Extract!$E:$E,"") -> 3.9 | E16: =_xlfn.XLOOKUP($B16,Raw_10K_Extract!$C:$C,Raw_10K_Extract!$F:$F,"") -> 4.9 | F16: Pulled from Raw_10K_Extract: Transactions per Active Consumer | G16: Consumer engagement frequency
A17: Balance Sheet | B17: Loans Held for Investment, Net | C17: =_xlfn.XLOOKUP($B17,Raw_10K_Extract!$C:$C,Raw_10K_Extract!$D:$D,"") -> 2348.169 | D17: =_xlfn.XLOOKUP($B17,Raw_10K_Extract!$C:$C,Raw_10K_Extract!$E:$E,"") -> 4198.431 | E17: =_xlfn.XLOOKUP($B17,Raw_10K_Extract!$C:$C,Raw_10K_Extract!$F:$F,"") -> 5360.959 | F17: Pulled from Raw_10K_Extract: Loans Held for Investment, Net | G17: Net loan exposure on balance sheet
A18: Balance Sheet | B18: Total Assets | C18: =_xlfn.XLOOKUP($B18,Raw_10K_Extract!$C:$C,Raw_10K_Extract!$D:$D,"") -> 6973.792 | D18: =_xlfn.XLOOKUP($B18,Raw_10K_Extract!$C:$C,Raw_10K_Extract!$E:$E,"") -> 8155.615 | E18: =_xlfn.XLOOKUP($B18,Raw_10K_Extract!$C:$C,Raw_10K_Extract!$F:$F,"") -> 9519.619 | F18: Pulled from Raw_10K_Extract: Total Assets | G18: Total company asset base
A19: Balance Sheet | B19: Total Liabilities | C19: =_xlfn.XLOOKUP($B19,Raw_10K_Extract!$C:$C,Raw_10K_Extract!$D:$D,"") -> 4355.537 | D19: =_xlfn.XLOOKUP($B19,Raw_10K_Extract!$C:$C,Raw_10K_Extract!$E:$E,"") -> 5621.432 | E19: =_xlfn.XLOOKUP($B19,Raw_10K_Extract!$C:$C,Raw_10K_Extract!$F:$F,"") -> 6787.63 | F19: Pulled from Raw_10K_Extract: Total Liabilities | G19: Total obligations
A20: Balance Sheet | B20: Total Stockholders' Equity | C20: =_xlfn.XLOOKUP($B20,Raw_10K_Extract!$C:$C,Raw_10K_Extract!$D:$D,"") -> 2618.255 | D20: =_xlfn.XLOOKUP($B20,Raw_10K_Extract!$C:$C,Raw_10K_Extract!$E:$E,"") -> 2534.183 | E20: =_xlfn.XLOOKUP($B20,Raw_10K_Extract!$C:$C,Raw_10K_Extract!$F:$F,"") -> 2731.989 | F20: Pulled from Raw_10K_Extract: Total Stockholders' Equity | G20: Book equity value
A21: Leverage | B21: Debt-to-Assets % | C21: =C19/C18 -> 0.62455792 | D21: =D19/D18 -> 0.68927138 | E21: =E19/E18 -> 0.71301488 | F21: Total Liabilities / Total Assets | G21: Total liabilities / total assets
A22: Capital Structure | B22: Equity Ratio % | C22: =C20/C18 -> 0.37544208 | D22: =D20/D18 -> 0.31072862 | E22: =E20/E18 -> 0.28698512 | F22: Total Stockholders' Equity / Total Assets | G22: Total equity / total assets

Sheet Income_Statement
A1: Affirm Holdings, Inc. - Income Statement
A2: USD millions
A4: Line Item | B4: FY2022 | C4: FY2023 | D4: FY2024 | E4: FY2023 YoY % | F4: FY2024 YoY %
A5: Merchant Network Revenue | B5: =Raw_10K_Extract!D9 -> 458.511 | C5: =Raw_10K_Extract!E9 -> 507.6 | D5: =Raw_10K_Extract!F9 -> 674.607 | E5: =IFERROR(C5/B5-1,"") -> 0.10706177 | F5: =IFERROR(D5/C5-1,"") -> 0.329013
A6: Card Network Revenue | B6: =Raw_10K_Extract!D10 -> 100.696 | C6: =Raw_10K_Extract!E10 -> 119.338 | D6: =Raw_10K_Extract!F10 -> 151.401 | E6: =IFERROR(C6/B6-1,"") -> 0.18513148 | F6: =IFERROR(D6/C6-1,"") -> 0.26867385
A7: Total Network Revenue | B7: =Raw_10K_Extract!D11 -> 559.207 | C7: =Raw_10K_Extract!E11 -> 626.938 | D7: =Raw_10K_Extract!F11 -> 826.008 | E7: =IFERROR(C7/B7-1,"") -> 0.12111973 | F7: =IFERROR(D7/C7-1,"") -> 0.31752741
A8: Interest Income | B8: =Raw_10K_Extract!D12 -> 527.88 | C8: =Raw_10K_Extract!E12 -> 685.217 | D8: =Raw_10K_Extract!F12 -> 1204.355 | E8: =IFERROR(C8/B8-1,"") -> 0.29805448 | F8: =IFERROR(D8/C8-1,"") -> 0.75762569
A9: Gain on Sales of Loans | B9: =Raw_10K_Extract!D13 -> 196.435 | C9: =Raw_10K_Extract!E13 -> 188.341 | D9: =Raw_10K_Extract!F13 -> 197.153 | E9: =IFERROR(C9/B9-1,"") -> -0.04120447 | F9: =IFERROR(D9/C9-1,"") -> 0.046787476
A10: Servicing Income | B10: =Raw_10K_Extract!D14 -> 65.77 | C10: =Raw_10K_Extract!E14 -> 87.489 | D10: =Raw_10K_Extract!F14 -> 95.483 | E10: =IFERROR(C10/B10-1,"") -> 0.33022655 | F10: =IFERROR(D10/C10-1,"") -> 0.091371487
A11: Revenue | B11: =Raw_10K_Extract!D15 -> 1349.292 | C11: =Raw_10K_Extract!E15 -> 1587.985 | D11: =Raw_10K_Extract!F15 -> 2322.999 | E11: =IFERROR(C11/B11-1,"") -> 0.17690241 | F11: =IFERROR(D11/C11-1,"") -> 0.46285954
E12: =IFERROR(C12/B12-1,"") | F12: =IFERROR(D12/C12-1,"")
A13: Loss on Loan Purchase Commitment | B13: =Raw_10K_Extract!D16 -> 204.081 | C13: =Raw_10K_Extract!E16 -> 140.265 | D13: =Raw_10K_Extract!F16 -> 180.395 | E13: =IFERROR(C13/B13-1,"") -> -0.31269937 | F13: =IFERROR(D13/C13-1,"") -> 0.28610131
A14: Provision for Credit Losses | B14: =Raw_10K_Extract!D17 -> 255.272 | C14: =Raw_10K_Extract!E17 -> 331.86 | D14: =Raw_10K_Extract!F17 -> 460.628 | E14: =IFERROR(C14/B14-1,"") -> 0.30002507 | F14: =IFERROR(D14/C14-1,"") -> 0.38801904
A15: Funding Costs | B15: =Raw_10K_Extract!D18 -> 69.694 | C15: =Raw_10K_Extract!E18 -> 183.013 | D15: =Raw_10K_Extract!F18 -> 344.253 | E15: =IFERROR(C15/B15-1,"") -> 1.6259506 | F15: =IFERROR(D15/C15-1,"") -> 0.88103031
A16: Processing and Servicing | B16: =Raw_10K_Extract!D19 -> 157.814 | C16: =Raw_10K_Extract!E19 -> 257.343 | D16: =Raw_10K_Extract!F19 -> 343.249 | E16: =IFERROR(C16/B16-1,"") -> 0.63067282 | F16: =IFERROR(D16/C16-1,"") -> 0.33381907
A17: Technology and Data Analytics | B17: =Raw_10K_Extract!D20 -> 418.643 | C17: =Raw_10K_Extract!E20 -> 615.818 | D17: =Raw_10K_Extract!F20 -> 501.857 | E17: =IFERROR(C17/B17-1,"") -> 0.47098602 | F17: =IFERROR(D17/C17-1,"") -> -0.1850563
A18: Sales and Marketing | B18: =Raw_10K_Extract!D21 -> 532.343 | C18: =Raw_10K_Extract!E21 -> 638.28 | D18: =Raw_10K_Extract!F21 -> 576.405 | E18: =IFERROR(C18/B18-1,"") -> 0.1990014 | F18: =IFERROR(D18/C18-1,"") -> -0.096940214
A19: General and Administrative | B19: =Raw_10K_Extract!D22 -> 577.493 | C19: =Raw_10K_Extract!E22 -> 586.398 | D19: =Raw_10K_Extract!F22 -> 525.291 | E19: =IFERROR(C19/B19-1,"") -> 0.0154201 | F19: =IFERROR(D19/C19-1,"") -> -0.10420738
A20: Restructuring and Other | B20: =Raw_10K_Extract!D23 -> 0 | C20: =Raw_10K_Extract!E23 -> 35.87 | D20: =Raw_10K_Extract!F23 -> 6.768 | E20: =IFERROR(C20/B20-1,"") | F20: =IFERROR(D20/C20-1,"") -> -0.81131865
A21: Total Operating Expenses | B21: =Raw_10K_Extract!D24 -> 2215.34 | C21: =Raw_10K_Extract!E24 -> 2788.847 | D21: =Raw_10K_Extract!F24 -> 2938.846 | E21: =IFERROR(C21/B21-1,"") -> 0.2588799 | F21: =IFERROR(D21/C21-1,"") -> 0.05378531
E22: =IFERROR(C22/B22-1,"") | F22: =IFERROR(D22/C22-1,"")
A23: Operating Income / Loss | B23: =Raw_10K_Extract!D25 -> -866.048 | C23: =Raw_10K_Extract!E25 -> -1200.862 | D23: =Raw_10K_Extract!F25 -> -615.847 | E23: =IFERROR(C23/B23-1,"") -> 0.38659982 | F23: =IFERROR(D23/C23-1,"") -> -0.48716255
A24: Other Income, Net | B24: =Raw_10K_Extract!D26 -> 141.217 | C24: =Raw_10K_Extract!E26 -> 211.617 | D24: =Raw_10K_Extract!F26 -> 100.32 | E24: =IFERROR(C24/B24-1,"") -> 0.49852355 | F24: =IFERROR(D24/C24-1,"") -> -0.52593601
A25: Loss Before Income Taxes | B25: =Raw_10K_Extract!D27 -> -724.831 | C25: =Raw_10K_Extract!E27 -> -989.245 | D25: =Raw_10K_Extract!F27 -> -515.527 | E25: =IFERROR(C25/B25-1,"") -> 0.364794 | F25: =IFERROR(D25/C25-1,"") -> -0.47886823
A26: Income Tax Expense / Benefit | B26: =Raw_10K_Extract!D28 -> -17.414 | C26: =Raw_10K_Extract!E28 -> -3.9 | D26: =Raw_10K_Extract!F28 -> 2.23 | E26: =IFERROR(C26/B26-1,"") -> -0.77604226 | F26: =IFERROR(D26/C26-1,"") -> -1.5717949
A27: Net Income / Loss | B27: =Raw_10K_Extract!D29 -> -707.417 | C27: =Raw_10K_Extract!E29 -> -985.345 | D27: =Raw_10K_Extract!F29 -> -517.757 | E27: =IFERROR(C27/B27-1,"") -> 0.39287719 | F27: =IFERROR(D27/C27-1,"") -> -0.47454242

Sheet Balance_Sheet
A1: Affirm Holdings, Inc. - Balance Sheet
A2: USD millions
A4: Line Item | B4: FY2022 | C4: FY2023 | D4: FY2024 | E4: FY2023 YoY % | F4: FY2024 YoY %
A5: Cash and Cash Equivalents | B5: =Raw_10K_Extract!D30 -> 1255.171 | C5: =Raw_10K_Extract!E30 -> 892.027 | D5: =Raw_10K_Extract!F30 -> 1013.106 | E5: =IFERROR(C5/B5-1,"") -> -0.28931835 | F5: =IFERROR(D5/C5-1,"") -> 0.13573468
A6: Restricted Cash | B6: =Raw_10K_Extract!D31 -> 295.636 | C6: =Raw_10K_Extract!E31 -> 367.917 | D6: =Raw_10K_Extract!F31 -> 282.293 | E6: =IFERROR(C6/B6-1,"") -> 0.24449323 | F6: =IFERROR(D6/C6-1,"") -> -0.2327264
A7: Securities Available for Sale | B7: =Raw_10K_Extract!D32 -> 1595.373 | C7: =Raw_10K_Extract!E32 -> 1174.653 | D7: =Raw_10K_Extract!F32 -> 1131.628 | E7: =IFERROR(C7/B7-1,"") -> -0.26371262 | F7: =IFERROR(D7/C7-1,"") -> -0.036627838
A8: Loans Held for Sale | B8: =Raw_10K_Extract!D33 -> 2.67 | C8: =Raw_10K_Extract!E33 -> 0.076 | D8: =Raw_10K_Extract!F33 -> 0.036 | E8: =IFERROR(C8/B8-1,"") -> -0.97153558 | F8: =IFERROR(D8/C8-1,"") -> -0.52631579
A9: Loans Held for Investment | B9: =Raw_10K_Extract!D34 -> 2503.561 | C9: =Raw_10K_Extract!E34 -> 4402.962 | D9: =Raw_10K_Extract!F34 -> 5670.056 | E9: =IFERROR(C9/B9-1,"") -> 0.75867974 | F9: =IFERROR(D9/C9-1,"") -> 0.28778218
A10: Allowance for Credit Losses | B10: =Raw_10K_Extract!D35 -> -155.392 | C10: =Raw_10K_Extract!E35 -> -204.531 | D10: =Raw_10K_Extract!F35 -> -309.097 | E10: =IFERROR(C10/B10-1,"") -> 0.31622606 | F10: =IFERROR(D10/C10-1,"") -> 0.51124768
A11: Loans Held for Investment, Net | B11: =Raw_10K_Extract!D36 -> 2348.169 | C11: =Raw_10K_Extract!E36 -> 4198.431 | D11: =Raw_10K_Extract!F36 -> 5360.959 | E11: =IFERROR(C11/B11-1,"") -> 0.78795947 | F11: =IFERROR(D11/C11-1,"") -> 0.27689582
A12: Accounts Receivable, Net | B12: =Raw_10K_Extract!D37 -> 142.052 | C12: =Raw_10K_Extract!E37 -> 199.085 | D12: =Raw_10K_Extract!F37 -> 353.028 | E12: =IFERROR(C12/B12-1,"") -> 0.40149382 | F12: =IFERROR(D12/C12-1,"") -> 0.77325263
A13: Property, Equipment and Software, Net | B13: =Raw_10K_Extract!D38 -> 171.482 | C13: =Raw_10K_Extract!E38 -> 290.135 | D13: =Raw_10K_Extract!F38 -> 427.686 | E13: =IFERROR(C13/B13-1,"") -> 0.69192685 | F13: =IFERROR(D13/C13-1,"") -> 0.47409309
A14: Goodwill | B14: =Raw_10K_Extract!D39 -> 539.534 | C14: =Raw_10K_Extract!E39 -> 542.571 | D14: =Raw_10K_Extract!F39 -> 533.439 | E14: =IFERROR(C14/B14-1,"") -> 0.0056289316 | F14: =IFERROR(D14/C14-1,"") -> -0.016830977
A15: Intangible Assets | B15: =Raw_10K_Extract!D40 -> 78.942 | C15: =Raw_10K_Extract!E40 -> 34.434 | D15: =Raw_10K_Extract!F40 -> 13.502 | E15: =IFERROR(C15/B15-1,"") -> -0.56380634 | F15: =IFERROR(D15/C15-1,"") -> -0.60788755
A16: Commercial Agreement Assets | B16: =Raw_10K_Extract!D41 -> 263.196 | C16: =Raw_10K_Extract!E41 -> 177.672 | D16: =Raw_10K_Extract!F41 -> 104.602 | E16: =IFERROR(C16/B16-1,"") -> -0.32494415 | F16: =IFERROR(D16/C16-1,"") -> -0.41126345
... A31: Total Liabilities and Stockholders' Equity | B31: =Raw_10K_Extract!D56 -> 6973.792 | C31: =Raw_10K_Extract!E56 -> 8155.615 | D31: =Raw_10K_Extract!F56 -> 9519.619 | E31: =IFERROR(C31/B31-1,"") -> 0.16946634 | F31: =IFERROR(D31/C31-1,"") -> 0.16724723
A32: Balance Check | B32: =B18-B31 -> 0 | C32: =C18-C31 -> 0 | D32: =D18-D31 -> 0

Sheet Cash_Flow
A1: Affirm Holdings, Inc. - Cash Flow Statement
A2: USD millions
A4: Line Item | B4: FY2022 | C4: FY2023 | D4: FY2024 | E4: FY2023 YoY % | F4: FY2024 YoY %
A5: Net Income / Loss | B5: =Raw_10K_Extract!D57 -> -707.417 | C5: =Raw_10K_Extract!E57 -> -985.345 | D5: =Raw_10K_Extract!F57 -> -517.757 | E5: =IFERROR(C5/B5-1,"") -> 0.39287719 | F5: =IFERROR(D5/C5-1,"") -> -0.47454242
A6: Depreciation and Amortization | B6: =Raw_10K_Extract!D58 -> 78.142 | C6: =Raw_10K_Extract!E58 -> 125.476 | D6: =Raw_10K_Extract!F58 -> 145.898 | E6: =IFERROR(C6/B6-1,"") -> 0.60574339 | F6: =IFERROR(D6/C6-1,"") -> 0.16275622
A7: Stock-Based Compensation | B7: =Raw_10K_Extract!D59 -> 396.162 | C7: =Raw_10K_Extract!E59 -> 478.998 | D7: =Raw_10K_Extract!F59 -> 339.572 | E7: =IFERROR(C7/B7-1,"") -> 0.20909628 | F7: =IFERROR(D7/C7-1,"") -> -0.29107846
A8: Provision for Credit Losses | B8: =Raw_10K_Extract!D60 -> 255.272 | C8: =Raw_10K_Extract!E60 -> 331.86 | D8: =Raw_10K_Extract!F60 -> 460.628 | E8: =IFERROR(C8/B8-1,"") -> 0.30002507 | F8: =IFERROR(D8/C8-1,"") -> 0.38801904
A9: Net Cash Used in Operating Activities | B9: =Raw_10K_Extract!D61 -> -276.624 | C9: =Raw_10K_Extract!E61 -> -392.075 | D9: =Raw_10K_Extract!F61 -> -356.332 | E9: =IFERROR(C9/B9-1,"") -> 0.41735713 | F9: =IFERROR(D9/C9-1,"") -> -0.09116368
A11: Purchases of Property, Equipment and Software | B11: =Raw_10K_Extract!D62 -> -136.337 | C11: =Raw_10K_Extract!E62 -> -225.452 | D11: =Raw_10K_Extract!F62 -> -263.204 | E11: =IFERROR(C11/B11-1,"") -> 0.65363768 | F11: =IFERROR(D11/C11-1,"") -> 0.16745028
A12: Net Cash Used in Investing Activities | B12: =Raw_10K_Extract!D63 -> -1684.709 | C12: =Raw_10K_Extract!E63 -> -1578.102 | D12: =Raw_10K_Extract!F63 -> -1231.105 | E12: =IFERROR(C12/B12-1,"") -> -0.063279178 | F12: =IFERROR(D12/C12-1,"") -> -0.21988249
A14: Net Cash Provided by Financing Activities | B14: =Raw_10K_Extract!D64 -> 1915.339 | C14: =Raw_10K_Extract!E64 -> 1829.566 | D14: =Raw_10K_Extract!F64 -> 1635.636 | E14: =IFERROR(C14/B14-1,"") -> -0.044782151 | F14: =IFERROR(D14/C14-1,"") -> -0.10599782
A16: Free Cash Flow | B16: =Raw_10K_Extract!D65 -> -412.961 | C16: =Raw_10K_Extract!E65 -> -617.527 | D16: =Raw_10K_Extract!F65 -> -619.536 | E16: =IFERROR(C16/B16-1,"") -> 0.49536397 | F16: =IFERROR(D16/C16-1,"") -> 0.003253299

Sheet Key_Metrics
A1: Affirm Holdings, Inc. - Key Metrics
A2: USD millions / ratios
A4: Metric | B4: FY2022 | C4: FY2023 | D4: FY2024 | E4: Trend | F4: Interpretation
A5: GMV | B5: =Clean_Financials!C2 -> 15483.237 | C5: =Clean_Financials!D2 -> 20200 | D5: =Clean_Financials!E2 -> 26600 | E5: =IF(A5="Active Consumer Growth %",IF(D5<C5,"Slowing",IF(D5>C5,"Accelerating","Stable")),IF(OR(A5="Credit Loss Rate %",A5="Debt-to-Assets %"),IF(D5<C5,"Improving",IF(D5>C5,"Worsening","Stable")),IF(D5>C5,"Improving",IF(D5<C5,"Worsening","Stable")))) -> Improving | F5: Platform volume is scaling
A6: Revenue | B6: =Clean_Financials!C3 -> 1349.292 | C6: =Clean_Financials!D3 -> 1587.985 | D6: =Clean_Financials!E3 -> 2322.999 | E6: =IF(A6="Active Consumer Growth %",IF(D6<C6,"Slowing",IF(D6>C6,"Accelerating","Stable")),IF(OR(A6="Credit Loss Rate %",A6="Debt-to-Assets %"),IF(D6<C6,"Improving",IF(D6>C6,"Worsening","Stable")),IF(D6>C6,"Improving",IF(D6<C6,"Worsening","Stable")))) -> Improving | F6: Revenue growth accelerated in FY2024
A7: GMV Growth % | B7: =Clean_Financials!C7 | C7: =Clean_Financials!D7 -> 0.30463675 | D7: =Clean_Financials!E7 -> 0.31683168 | E7: =IF(A7="Active Consumer Growth %",IF(D7<C7,"Slowing",IF(D7>C7,"Accelerating","Stable")),IF(OR(A7="Credit Loss Rate %",A7="Debt-to-Assets %"),IF(D7<C7,"Improving",IF(D7>C7,"Worsening","Stable")),IF(D7>C7,"Improving",IF(D7<C7,"Worsening","Stable")))) -> Improving | F7: GMV growth remained strong
A8: Revenue Growth % | B8: =Clean_Financials!C8 | C8: =Clean_Financials!D8 -> 0.17690241 | D8: =Clean_Financials!E8 -> 0.46285954 | E8: =IF(A8="Active Consumer Growth %",IF(D8<C8,"Slowing",IF(D8>C8,"Accelerating","Stable")),IF(OR(A8="Credit Loss Rate %",A8="Debt-to-Assets %"),IF(D8<C8,"Improving",IF(D8>C8,"Worsening","Stable")),IF(D8>C8,"Improving",IF(D8<C8,"Worsening","Stable")))) -> Improving | F8: Revenue grew faster than GMV in FY2024
A9: Take Rate % | B9: =Clean_Financials!C9 -> 0.087145343 | C9: =Clean_Financials!D9 -> 0.078613119 | D9: =Clean_Financials!E9 -> 0.087330789 | E9: =IF(A9="Active Consumer Growth %",IF(D9<C9,"Slowing",IF(D9>C9,"Accelerating","Stable")),IF(OR(A9="Credit Loss Rate %",A9="Debt-to-Assets %"),IF(D9<C9,"Improving",IF(D9>C9,"Worsening","Stable")),IF(D9>C9,"Improving",IF(D9<C9,"Worsening","Stable")))) -> Improving | F9: Revenue generated per dollar of GMV
A10: Credit Loss Rate % | B10: =Clean_Financials!C10 -> 0.016486992 | C10: =Clean_Financials!D10 -> 0.012637228 | D10: =Clean_Financials!E10 -> 0.0095966917 | E10: =IF(A10="Active Consumer Growth %",IF(D10<C10,"Slowing",IF(D10>C10,"Accelerating","Stable")),IF(OR(A10="Credit Loss Rate %",A10="Debt-to-Assets %"),IF(D10<C10,"Improving",IF(D10>C10,"Worsening","Stable")),IF(D10>C10,"Improving",IF(D10<C10,"Worsening","Stable")))) -> Improving | F10: Credit losses remain controlled but should be monitored
A11: Operating Margin % | B11: =Clean_Financials!C11 -> -0.64185365 | C11: =Clean_Financials!D11 -> -0.75621747 | D11: =Clean_Financials!E11 -> -0.26510859 | E11: =IF(A11="Active Consumer Growth %",IF(D11<C11,"Slowing",IF(D11>C11,"Accelerating","Stable")),IF(OR(A11="Credit Loss Rate %",A11="Debt-to-Assets %"),IF(D11<C11,"Improving",IF(D11>C11,"Worsening","Stable")),IF(D11>C11,"Improving",IF(D11<C11,"Worsening","Stable")))) -> Improving | F11: FY2024 operating loss narrowed significantly
A12: Net Margin % | B12: =Clean_Financials!C12 -> -0.52428755 | C12: =Clean_Financials!D12 -> -0.62050019 | D12: =Clean_Financials!E12 -> -0.22288301 | E12: =IF(A12="Active Consumer Growth %",IF(D12<C12,"Slowing",IF(D12>C12,"Accelerating","Stable")),IF(OR(A12="Credit Loss Rate %",A12="Debt-to-Assets %"),IF(D12<C12,"Improving",IF(D12>C12,"Worsening","Stable")),IF(D12>C12,"Improving",IF(D12<C12,"Worsening","Stable")))) -> Improving | F12: Net loss narrowed significantly in FY2024
A13: Free Cash Flow Margin % | B13: =Clean_Financials!C13 -> -0.30605755 | C13: =Clean_Financials!D13 -> -0.38887458 | D13: =Clean_Financials!E13 -> -0.26669663 | E13: =IF(A13="Active Consumer Growth %",IF(D13<C13,"Slowing",IF(D13>C13,"Accelerating","Stable")),IF(OR(A13="Credit Loss Rate %",A13="Debt-to-Assets %"),IF(D13<C13,"Improving",IF(D13>C13,"Worsening","Stable")),IF(D13>C13,"Improving",IF(D13<C13,"Worsening","Stable")))) -> Improving | F13: Free cash flow remained negative despite revenue growth
A14: Active Consumers | B14: =Clean_Financials!C14 -> 13.98 | C14: =Clean_Financials!D14 -> 16.469 | D14: =Clean_Financials!E14 -> 18.713 | E14: =IF(A14="Active Consumer Growth %",IF(D14<C14,"Slowing",IF(D14>C14,"Accelerating","Stable")),IF(OR(A14="Credit Loss Rate %",A14="Debt-to-Assets %"),IF(D14<C14,"Improving",IF(D14>C14,"Worsening","Stable")),IF(D14>C14,"Improving",IF(D14<C14,"Worsening","Stable")))) -> Improving | F14: Consumer base expanded
A15: Active Consumer Growth % | B15: =Clean_Financials!C15 | C15: =Clean_Financials!D15 -> 0.17804006 | D15: =Clean_Financials!E15 -> 0.136256 | E15: =IF(A15="Active Consumer Growth %",IF(D15<C15,"Slowing",IF(D15>C15,"Accelerating","Stable")),IF(OR(A15="Credit Loss Rate %",A15="Debt-to-Assets %"),IF(D15<C15,"Improving",IF(D15>C15,"Worsening","Stable")),IF(D15>C15,"Improving",IF(D15<C15,"Worsening","Stable")))) -> Slowing | F15: Consumer growth slowed from FY2023 to FY2024
A16: Transactions per Active Consumer | B16: =Clean_Financials!C16 -> 3 | C16: =Clean_Financials!D16 -> 3.9 | D16: =Clean_Financials!E16 -> 4.9 | E16: =IF(A16="Active Consumer Growth %",IF(D16<C16,"Slowing",IF(D16>C16,"Accelerating","Stable")),IF(OR(A16="Credit Loss Rate %",A16="Debt-to-Assets %"),IF(D16<C16,"Improving",IF(D16>C16,"Worsening","Stable")),IF(D16>C16,"Improving",IF(D16<C16,"Worsening","Stable")))) -> Improving | F16: Customer engagement improved
A17: Debt-to-Assets % | B17: =Clean_Financials!C21 -> 0.62455792 | C17: =Clean_Financials!D21 -> 0.68927138 | D17: =Clean_Financials!E21 -> 0.71301488 | E17: =IF(A17="Active Consumer Growth %",IF(D17<C17,"Slowing",IF(D17>C17,"Accelerating","Stable")),IF(OR(A17="Credit Loss Rate %",A17="Debt-to-Assets %"),IF(D17<C17,"Improving",IF(D17>C17,"Worsening","Stable")),IF(D17>C17,"Improving",IF(D17<C17,"Worsening","Stable")))) -> Worsening | F17: Balance sheet leverage increased
A18: Equity Ratio % | B18: =Clean_Financials!C22 -> 0.37544208 | C18: =Clean_Financials!D22 -> 0.31072862 | D18: =Clean_Financials!E22 -> 0.28698512 | E18: =IF(A18="Active Consumer Growth %",IF(D18<C18,"Slowing",IF(D18>C18,"Accelerating","Stable")),IF(OR(A18="Credit Loss Rate %",A18="Debt-to-Assets %"),IF(D18<C18,"Improving",IF(D18>C18,"Worsening","Stable")),IF(D18>C18,"Improving",IF(D18<C18,"Worsening","Stable")))) -> Worsening | F18: Equity share of assets declined

Sheet Assumptions
A1: Affirm Holdings, Inc. - Forecast Assumptions
A2: USD millions / ratios
A4: Assumption | B4: Base Case | C4: Bull Case | D4: Bear Case | E4: Selected Case | F4: Selected Value
A5: Revenue Growth FY2025 | B5: 0.25 | C5: 0.35 | D5: 0.15 | E5: Base Case | F5: =IF(E5="Base Case",B5,IF(E5="Bull Case",C5,IF(E5="Bear Case",D5,""))) -> 0.25
A6: Revenue Growth FY2026 | B6: 0.2 | C6: 0.28 | D6: 0.1 | E6: Base Case | F6: =IF(E6="Base Case",B6,IF(E6="Bull Case",C6,IF(E6="Bear Case",D6,""))) -> 0.2
A7: Revenue Growth FY2027 | B7: 0.16 | C7: 0.22 | D7: 0.08 | E7: Base Case | F7: =IF(E7="Base Case",B7,IF(E7="Bull Case",C7,IF(E7="Bear Case",D7,""))) -> 0.16
A8: Revenue Growth FY2028 | B8: 0.12 | C8: 0.18 | D8: 0.06 | E8: Base Case | F8: =IF(E8="Base Case",B8,IF(E8="Bull Case",C8,IF(E8="Bear Case",D8,""))) -> 0.12
A9: Revenue Growth FY2029 | B9: 0.1 | C9: 0.15 | D9: 0.05 | E9: Base Case | F9: =IF(E9="Base Case",B9,IF(E9="Bull Case",C9,IF(E9="Bear Case",D9,""))) -> 0.1
A10: Operating Margin FY2025 | B10: -0.15 | C10: -0.08 | D10: -0.25 | E10: Base Case | F10: =IF(E10="Base Case",B10,IF(E10="Bull Case",C10,IF(E10="Bear Case",D10,""))) -> -0.15
A11: Operating Margin FY2026 | B11: -0.08 | C11: 0.02 | D11: -0.18 | E11: Base Case | F11: =IF(E11="Base Case",B11,IF(E11="Bull Case",C11,IF(E11="Bear Case",D11,""))) -> -0.08
A12: Operating Margin FY2027 | B12: 0.02 | C12: 0.08 | D12: -0.1 | E12: Base Case | F12: =IF(E12="Base Case",B12,IF(E12="Bull Case",C12,IF(E12="Bear Case",D12,""))) -> 0.02
A13: Operating Margin FY2028 | B13: 0.06 | C13: 0.12 | D13: -0.05 | E13: Base Case | F13: =IF(E13="Base Case",B13,IF(E13="Bull Case",C13,IF(E13="Bear Case",D13,""))) -> 0.06
A14: Operating Margin FY2029 | B14: 0.1 | C14: 0.16 | D14: 0 | E14: Base Case | F14: =IF(E14="Base Case",B14,IF(E14="Bull Case",C14,IF(E14="Bear Case",D14,""))) -> 0.1
A15: Tax Rate | B15: 0.21 | C15: 0.21 | D15: 0.21 | E15: Base Case | F15: =IF(E15="Base Case",B15,IF(E15="Bull Case",C15,IF(E15="Bear Case",D15,""))) -> 0.21
A16: D&A % of Revenue | B16: 0.06 | C16: 0.05 | D16: 0.07 | E16: Base Case | F16: =IF(E16="Base Case",B16,IF(E16="Bull Case",C16,IF(E16="Bear Case",D16,""))) -> 0.06
... A20: Terminal Growth Rate | B20: 0.03 | C20: 0.04 | D20: 0.02 | E20: Base Case | F20: =IF(E20="Base Case",B20,IF(E20="Bull Case",C20,IF(E20="Bear Case",D20,""))) -> 0.03

Sheet Forecast_Model
A1: Affirm Holdings, Inc. - Forecast Model
A2: USD millions / ratios
A4: Line Item | B4: FY2024A | C4: FY2025F | D4: FY2026F | E4: FY2027F | F4: FY2028F | G4: FY2029F
A5: Revenue | B5: =Clean_Financials!E3 -> 2322.999 | C5: =B5*(1+Assumptions!F5) -> 2903.7487 | D5: =C5*(1+Assumptions!F6) -> 3484.4985 | E5: =D5*(1+Assumptions!F7) -> 4042.0183 | F5: =E5*(1+Assumptions!F8) -> 4527.0605 | G5: =F5*(1+Assumptions!F9) -> 4979.7665
A6: Revenue Growth % | B6: =Clean_Financials!E8 -> 0.46285954 | C6: =Assumptions!F5 -> 0.25 | D6: =Assumptions!F6 -> 0.2 | E6: =Assumptions!F7 -> 0.16 | F6: =Assumptions!F8 -> 0.12 | G6: =Assumptions!F9 -> 0.1
A7: Operating Margin % | B7: =Clean_Financials!E11 -> -0.26510859 | C7: =Assumptions!F10 -> -0.15 | D7: =Assumptions!F11 -> -0.08 | E7: =Assumptions!F12 -> 0.02 | F7: =Assumptions!F13 -> 0.06 | G7: =Assumptions!F14 -> 0.1
A8: Operating Income / Loss | B8: =B5*B7 -> -615.847 | C8: =C5*C7 -> -435.56231 | D8: =D5*D7 -> -278.75988 | E8: =E5*E7 -> 80.840365 | F8: =F5*F7 -> 271.62363 | G8: =G5*G7 -> 497.97665
A9: Tax Rate | C9: =Assumptions!F15 -> 0.21 | D9: =Assumptions!F15 -> 0.21 | E9: =Assumptions!F15 -> 0.21 | F9: =Assumptions!F15 -> 0.21 | G9: =Assumptions!F15 -> 0.21
A10: Tax Expense | C10: =IF(C8>0,C8*C9,0) -> 0 | D10: =IF(D8>0,D8*D9,0) -> 0 | E10: =IF(E8>0,E8*E9,0) -> 16.976477 | F10: =IF(F8>0,F8*F9,0) -> 57.040962 | G10: =IF(G8>0,G8*G9,0) -> 104.5751
A11: NOPAT | C11: =C8-C10 -> -435.56231 | D11: =D8-D10 -> -278.75988 | E11: =E8-E10 -> 63.863889 | F11: =F8-F10 -> 214.58267 | G11: =G8-G10 -> 393.40155
A12: D&A % of Revenue | C12: =Assumptions!F16 -> 0.06 | D12: =Assumptions!F16 -> 0.06 | E12: =Assumptions!F16 -> 0.06 | F12: =Assumptions!F16 -> 0.06 | G12: =Assumptions!F16 -> 0.06
A13: D&A | C13: =C5*C12 -> 174.22492 | D13: =D5*D12 -> 209.06991 | E13: =E5*E12 -> 242.5211 | F13: =F5*F12 -> 271.62363 | G13: =G5*G12 -> 298.78599
A14: Capex % of Revenue | C14: =Assumptions!F17 -> 0.09 | D14: =Assumptions!F17 -> 0.09 | E14: =Assumptions!F17 -> 0.09 | F14: =Assumptions!F17 -> 0.09 | G14: =Assumptions!F17 -> 0.09
A15: Capex | C15: =-(C5*C14) -> -261.33739 | D15: =-(D5*D14) -> -313.60486 | E15: =-(E5*E14) -> -363.78164 | F15: =-(F5*F14) -> -407.43544 | G15: =-(G5*G14) -> -448.17898
A16: Change in NWC % of Revenue | C16: =Assumptions!F18 -> 0.03 | D16: =Assumptions!F18 -> 0.03 | E16: =Assumptions!F18 -> 0.03 | F16: =Assumptions!F18 -> 0.03 | G16: =Assumptions!F18 -> 0.03
A17: Change in NWC | C17: =-(C5*C16) -> -87.112462 | D17: =-(D5*D16) -> -104.53495 | E17: =-(E5*E16) -> -121.26055 | F17: =-(F5*F16) -> -135.81181 | G17: =-(G5*G16) -> -149.39299
A18: Free Cash Flow | B18: =Clean_Financials!E6 -> -619.536 | C18: =C11+C13+C15+C17 -> -609.78724 | D18: =D11+D13+D15+D17 -> -487.82979 | E18: =E11+E13+E15+E17 -> -178.65721 | F18: =F11+F13+F15+F17 -> -57.040962 | G18: =G11+G13+G15+G17 -> 94.615563

Sheet DCF_Valuation
A1: Affirm Holdings, Inc. - DCF Valuation
A2: USD millions / ratios
A4: Line Item | B4: FY2025F | C4: FY2026F | D4: FY2027F | E4: FY2028F | F4: FY2029F | G4: Terminal Value
A5: Free Cash Flow | B5: =Forecast_Model!C18 -> -609.78724 | C5: =Forecast_Model!D18 -> -487.82979 | D5: =Forecast_Model!E18 -> -178.65721 | E5: =Forecast_Model!F18 -> -57.040962 | F5: =Forecast_Model!G18 -> 94.615563
A6: Discount Period | B6: 1 | C6: 2 | D6: 3 | E6: 4 | F6: 5
A7: WACC | B7: =Assumptions!F19 -> 0.12 | C7: =Assumptions!F19 -> 0.12 | D7: =Assumptions!F19 -> 0.12 | E7: =Assumptions!F19 -> 0.12 | F7: =Assumptions!F19 -> 0.12
A8: Discount Factor | B8: =1/(1+B7)^B6 -> 0.89285714 | C8: =1/(1+C7)^C6 -> 0.79719388 | D8: =1/(1+D7)^D6 -> 0.71178025 | E8: =1/(1+E7)^E6 -> 0.63551808 | F8: =1/(1+F7)^F6 -> 0.56742686
A9: PV of Free Cash Flow | B9: =B5*B8 -> -544.45289 | C9: =C5*C8 -> -388.89492 | D9: =D5*D8 -> -127.16467 | E9: =E5*E8 -> -36.250562 | F9: =F5*F8 -> 53.687412
A10: Terminal Growth Rate | G10: =Assumptions!F20 -> 0.03
A11: Terminal Value | G11: =F5*(1+G10)/(F7-G10) -> 1082.8226
A12: PV of Terminal Value | G12: =G11*F8 -> 614.4226
A13: Enterprise Value | G13: =SUM(B9:F9)+G12 -> -428.65303

Sheet Variance_Analysis
A1: Affirm Holdings, Inc. - Variance Analysis
A2: USD millions / ratios
A4: Metric | B4: FY2022 Actual | C4: Budget Assumption | D4: FY2023 Budget | E4: FY2023 Actual | F4: Variance $ / pts | G4: Variance % | H4: Status | I4: Interpretation
A5: GMV | B5: =Clean_Financials!C2 -> 15483.237 | C5: 0.25 | D5: =B5*(1+C5) -> 19354.046 | E5: =Clean_Financials!D2 -> 20200 | F5: =E5-D5 -> 845.95375 | G5: =F5/D5 -> 0.0437094 | H5: =IF(F5>=0,"Favorable","Unfavorable") -> Favorable | I5: Actual GMV compared with budgeted platform volume
A6: Revenue | B6: =Clean_Financials!C3 -> 1349.292 | C6: 0.2 | D6: =B6*(1+C6) -> 1619.1504 | E6: =Clean_Financials!D3 -> 1587.985 | F6: =E6-D6 -> -31.1654 | G6: =F6/D6 -> -0.019247996 | H6: =IF(F6>=0,"Favorable","Unfavorable") -> Unfavorable | I6: Actual revenue compared with budgeted revenue
A7: Total Operating Expenses | B7: =Raw_10K_Extract!D24 -> 2215.34 | C7: 0.15 | D7: =B7*(1+C7) -> 2547.641 | E7: =Raw_10K_Extract!E24 -> 2788.847 | F7: =E7-D7 -> 241.206 | G7: =F7/D7 -> 0.094678175 | H7: =IF(F7<=0,"Favorable","Unfavorable") -> Unfavorable | I7: For expenses, lower than budget is favorable
A8: Operating Income / Loss | B8: =Clean_Financials!C4 -> -866.048 | C8: 10% improvement | D8: =B8*0.9 -> -779.4432 | E8: =Clean_Financials!D4 -> -1200.862 | F8: =E8-D8 -> -421.4188 | G8: =F8/ABS(D8) -> -0.54066647 | H8: =IF(E8>D8,"Favorable","Unfavorable") -> Unfavorable | I8: Operating loss should narrow versus budget
A9: Net Income / Loss | B9: =Clean_Financials!C5 -> -707.417 | C9: 10% improvement | D9: =B9*0.9 -> -636.6753 | E9: =Clean_Financials!D5 -> -985.345 | F9: =E9-D9 -> -348.6697 | G9: =F9/ABS(D9) -> -0.54764132 | H9: =IF(E9>D9,"Favorable","Unfavorable") -> Unfavorable | I9: Net loss should narrow versus budget
A10: Free Cash Flow | B10: =Clean_Financials!C6 -> -412.961 | C10: 5% improvement | D10: =B10*0.95 -> -392.31295 | E10: =Clean_Financials!D6 -> -617.527 | F10: =E10-D10 -> -225.21405 | G10: =F10/ABS(D10) -> -0.57406734 | H10: =IF(E10>D10,"Favorable","Unfavorable") -> Unfavorable | I10: Free cash flow should improve versus budget
A11: Active Consumers | B11: =Clean_Financials!C14 -> 13.98 | C11: 0.15 | D11: =B11*(1+C11) -> 16.077 | E11: =Clean_Financials!D14 -> 16.469 | F11: =E11-D11 -> 0.392 | G11: =F11/D11 -> 0.024382658 | H11: =IF(F11>=0,"Favorable","Unfavorable") -> Favorable | I11: Actual active consumers compared with budgeted consumer growth

Sheet Scenario_Analysis
A1: Affirm Holdings, Inc. - Scenario Analysis
A2: USD millions / ratios
A4: Metric | B4: Base Case | C4: Bull Case | D4: Bear Case | E4: Interpretation
A5: FY2029 Revenue | B5: 4979.8 | C5: 6414.5 | D5: 3640.3 | E5: Revenue outcome under each scenario
A6: FY2029 Operating Margin % | B6: 0.1 | C6: 0.16 | D6: 0 | E6: Profitability assumption by scenario
A7: FY2029 Operating Income | B7: 498 | C7: 1026.3 | D7: 0 | E7: Revenue × operating margin
A8: FY2029 Free Cash Flow | B8: 94.6 | C8: 513.2 | D8: -618.9 | E8: Cash generation after reinvestment
A9: WACC | B9: 0.12 | C9: 0.1 | D9: 0.14 | E9: Discount rate / business risk
A10: Terminal Growth Rate | B10: 0.03 | C10: 0.04 | D10: 0.02 | E10: Long-term growth assumption
A11: DCF Enterprise Value | B11: -428.7 | C11: 4412.5 | D11: -5054.8 | E11: Estimated value under each case
A12: Scenario View | B12: Base case shows delayed free cash flow recovery | C12: Bull case assumes faster profitability | D12: Bear case assumes weak margin recovery | E12: Shows valuation sensitivity to assumptions

Sheet Benchmark
A1: Affirm Holdings, Inc. - Benchmark
A2: USD billions / ratios
A4: Metric | B4: Affirm | C4: Klarna | D4: Industry / Benchmark | E4: Interpretation | F4: Notes
A5: GMV | B5: 26.6 | C5: 105 | D5: BNPL peers vary widely | E5: Klarna is much larger by transaction volume | F5: Affirm GMV in USD billions; Klarna approximate FY2024 GMV in USD billions
A6: Revenue | B6: 2.3 | C6: 2.8 | D6: Revenue scale depends on business model | E6: Klarna has larger revenue scale, but comparison is directional | F6: Affirm revenue in USD billions; Klarna approximate FY2024 revenue in USD billions
A7: Take Rate % | B7: 0.087 | C7: 0.027 | D7: 3% - 9% range | E7: Affirm monetizes GMV at a higher rate than Klarna | F7: Revenue / GMV
A8: Credit Loss Rate % | B8: 0.017 | C8: 0.006 | D8: Lower is better | E8: Affirm credit loss rate appears higher on this simplified comparison | F8: Credit loss / GMV
A9: Operating Margin % | B9: -0.265 | C9: -0.043 | D9: Positive margin is stronger | E9: Klarna was closer to operating break-even than Affirm | F9: Operating income / revenue
A10: Active Consumers | B10: 18.7 | C10: 93 | D10: Scale differs significantly | E10: Klarna has a much larger consumer base | F10: Affirm in millions; Klarna approximate active consumers in millions
A11: Active Merchants | B11: 303 | C11: 675 | D11: Merchant network size matters | E11: Klarna has broader merchant reach | F11: Affirm and Klarna in thousands
A12: Reporting Basis | B12: US GAAP | C12: IFRS | D12: Not directly comparable | E12: Accounting differences limit direct comparison | F12: Use as directional benchmark only
A13: Currency | B13: USD | C13: Mostly SEK / USD disclosed | D13: Convert carefully | E13: Currency differences can distort comparison | F13: Do not mix without clear notes
A18: Benchmarking limitation: Klarna is included only as a directional peer benchmark. Direct comparison is limited because Affirm reports under US GAAP in USD, while Klarna reports under IFRS and has different revenue recognition, funding structure, product mix, and currency presentation.

Sheet Output_Summary
A1: Affirm Holdings, Inc. - Executive Output Summary
A2: Financial Modeling Summary
A3: USD millions / ratios; GMV shown in USD millions
A4: Section | B4: Metric / Finding | C4: FY2022 | D4: FY2023 | E4: FY2024 / Forecast | F4: Analyst Interpretation
A5: Scale | B5: GMV | C5: 15483.2 | D5: 20200 | E5: 26600 | F5: Affirm’s platform volume scaled strongly from FY2022 to FY2024.
A6: Scale | B6: Revenue | C6: 1349.3 | D6: 1588 | E6: 2323 | F6: Revenue accelerated in FY2024, growing faster than GMV.
A7: Efficiency | B7: Take Rate % | C7: 0.087 | D7: 0.079 | E7: 0.087 | F7: Take rate recovered in FY2024 after compression in FY2023.
A8: Credit Risk | B8: Credit Loss Rate % | C8: 0.016 | D8: 0.016 | E8: 0.017 | F8: Credit loss rate remained relatively controlled but needs monitoring.
A9: Profitability | B9: Operating Margin % | C9: -0.642 | D9: -0.756 | E9: -0.265 | F9: Operating margin improved sharply in FY2024 but remains negative.
A10: Profitability | B10: Net Margin % | C10: -0.524 | D10: -0.621 | E10: -0.223 | F10: Net loss narrowed significantly in FY2024.
A11: Cash Flow | B11: Free Cash Flow | C11: -413 | D11: -617.5 | E11: -619.5 | F11: Free cash flow remained negative despite revenue growth.
A12: Customer | B12: Active Consumers | C12: 14 | D12: 16.5 | E12: 18.7 | F12: Active consumer base continued expanding.
A13: Engagement | B13: Transactions per Active Consumer | C13: 3 | D13: 3.9 | E13: 4.9 | F13: Customer engagement improved year over year.
A14: Leverage | B14: Debt-to-Assets % | C14: 0.625 | D14: 0.689 | E14: 0.713 | F14: Balance sheet leverage increased.
A15: Forecast | B15: Base Case FY2029 Revenue | E15: 4979.8 | F15: Base Case assumes revenue reaches approximately $5.0B by FY2029.
A16: Forecast | B16: Base Case FY2029 Free Cash Flow | E16: 94.6 | F16: Base Case turns free-cash-flow positive by FY2029.
A17: Valuation | B17: Base Case DCF Enterprise Value | E17: -428.7 | F17: DCF remains negative under Base Case due to near-term cash burn.
A18: Scenario | B18: Bull Case DCF Enterprise Value | E18: 4412.5 | F18: Bull Case creates positive value through stronger growth and margin expansion.
A19: Scenario | B19: Bear Case DCF Enterprise Value | E19: -5054.8 | F19: Bear Case shows downside risk if profitability recovery is weak.
A24: Executive Conclusion:
A26: 1. Affirm scaled strongly from FY2022 to FY2024, with GMV rising from $15.5B to $26.6B and revenue increasing from $1.3B to $2.3B. Revenue growth accelerated in FY2024, and operating margin improved sharply as losses narrowed. However, the company remains unprofitable and free-cash-flow negative, while leverage increased over the same period.
A28: 2. The Base Case forecast assumes gradual revenue growth normalization and margin improvement, with Affirm turning free-cash-flow positive by FY2029. The DCF valuation remains negative in the Base Case because near-term cash burn offsets terminal value. The Bull Case shows meaningful upside if Affirm achieves faster profitability and stronger free cash flow recovery, while the Bear Case highlights downside risk from weak margins, higher risk, and slower growth.
A30: 3. Overall, Affirm appears to be a high-growth fintech platform with improving operating leverage, but its long-term value depends on sustained revenue growth, disciplined credit risk management, margin expansion, and free cash flow recovery.
